hskl/__init__.py
hskl/base.py
hskl/classification.py
hskl/demo.py
hskl/regression.py
hskl/utils.py
hskl-0.0.2.dist-info/LICENSE
hskl-0.0.2.dist-info/METADATA
hskl-0.0.2.dist-info/WHEEL
hskl-0.0.2.dist-info/top_level.txt
hskl-0.0.2.dist-info/RECORD
