Metadata-Version: 2.1
Name: hskl
Version: 0.0.2
Summary: Hyperspectral image analysis with scikit-learn.
Home-page: https://github.com/qiancao/hskl
Author: Qian Cao
Author-email: qcao.dev@gmail.com
License: UNKNOWN
Platform: UNKNOWN
Classifier: Programming Language :: Python :: 3
Classifier: License :: OSI Approved :: BSD License
Classifier: Operating System :: OS Independent
Requires-Python: >=3.6
Requires-Dist: numpy
Requires-Dist: scikit-learn
Requires-Dist: multimethod
Requires-Dist: matplotlib
Requires-Dist: spectral
Requires-Dist: h5py
Requires-Dist: scipy
Requires-Dist: tqdm
Requires-Dist: scikit-image
